gobeautifulsoup/__init__.py
gobeautifulsoup/_bindings.py
gobeautifulsoup/element.py
gobeautifulsoup/soup.py
gobeautifulsoup-1.0.0.dist-info/licenses/LICENSE
gobeautifulsoup-1.0.0.dist-info/METADATA
gobeautifulsoup-1.0.0.dist-info/WHEEL
gobeautifulsoup-1.0.0.dist-info/top_level.txt
gobeautifulsoup-1.0.0.dist-info/RECORD
