Metadata-Version: 2.4
Name: gobeautifulsoup
Version: 1.0.0
Summary: A high-performance BeautifulSoup replacement powered by Go
Home-page: https://github.com/coffeecms/gobeautifulsoup
Author: CoffeeCMS Team
Author-email: CoffeeCMS Team <team@coffeecms.com>
Maintainer-email: CoffeeCMS Team <team@coffeecms.com>
License: MIT License
Project-URL: Homepage, https://github.com/coffeecms/gobeautifulsoup
Project-URL: Bug Reports, https://github.com/coffeecms/gobeautifulsoup/issues
Project-URL: Source, https://github.com/coffeecms/gobeautifulsoup
Project-URL: Documentation, https://gobeautifulsoup.readthedocs.io/
Project-URL: Changelog, https://github.com/coffeecms/gobeautifulsoup/blob/main/CHANGELOG.md
Project-URL: Benchmarks, https://github.com/coffeecms/gobeautifulsoup/tree/main/benchmarks
Keywords: html,xml,parsing,beautifulsoup,go,performance,web-scraping
Classifier: Development Status :: 5 - Production/Stable
Classifier: Intended Audience :: Developers
Classifier: License :: OSI Approved :: MIT License
Classifier: Operating System :: OS Independent
Classifier: Programming Language :: Python :: 3
Classifier: Programming Language :: Python :: 3.7
Classifier: Programming Language :: Python :: 3.8
Classifier: Programming Language :: Python :: 3.9
Classifier: Programming Language :: Python :: 3.10
Classifier: Programming Language :: Python :: 3.11
Classifier: Programming Language :: Python :: 3.12
Classifier: Topic :: Software Development :: Libraries :: Python Modules
Classifier: Topic :: Text Processing :: Markup :: HTML
Classifier: Topic :: Text Processing :: Markup :: XML
Classifier: Topic :: Internet :: WWW/HTTP :: Dynamic Content
Requires-Python: >=3.7
License-File: LICENSE
Provides-Extra: dev
Requires-Dist: pytest>=6.0; extra == "dev"
Requires-Dist: beautifulsoup4>=4.10.0; extra == "dev"
Requires-Dist: lxml>=4.6.0; extra == "dev"
Requires-Dist: black>=21.0.0; extra == "dev"
Requires-Dist: flake8>=3.9.0; extra == "dev"
Requires-Dist: mypy>=0.991; extra == "dev"
Requires-Dist: requests>=2.25.0; extra == "dev"
Provides-Extra: test
Requires-Dist: pytest>=6.0; extra == "test"
Requires-Dist: beautifulsoup4>=4.10.0; extra == "test"
Requires-Dist: lxml>=4.6.0; extra == "test"
Requires-Dist: requests>=2.25.0; extra == "test"
Provides-Extra: benchmark
Requires-Dist: beautifulsoup4>=4.10.0; extra == "benchmark"
Requires-Dist: lxml>=4.6.0; extra == "benchmark"
Requires-Dist: memory-profiler>=0.60.0; extra == "benchmark"
Requires-Dist: requests>=2.25.0; extra == "benchmark"
Dynamic: author
Dynamic: home-page
Dynamic: license-file
Dynamic: requires-python
